{
  "type": "python",
  "neverRecomputeExistingPartitions": false,
  "optionalDependencies": false,
  "params": {
    "envSelection": {
      "envMode": "INHERIT"
    },
    "containerSelection": {
      "containerMode": "INHERIT"
    },
    "skipPrerunValidate": false
  },
  "customMeta": {
    "kv": {}
  },
  "redispatchPartitioning": false,
  "maxRunningActivities": 0,
  "variables": {},
  "dkuProperties": [],
  "inputs": {
    "main": {
      "items": [
        {
          "ref": "TRANSACTIONS_prepared",
          "deps": []
        }
      ]
    }
  },
  "outputs": {
    "main": {
      "items": [
        {
          "ref": "TRANSACTIONS_filtered_z_score",
          "appendMode": false
        }
      ]
    }
  },
  "labels": [],
  "versionTag": {
    "versionNumber": 2,
    "lastModifiedBy": {
      "login": "patrick.masi-phelps@dataiku.com"
    },
    "lastModifiedOn": 1694478290983,
    "extendedProperties": {}
  },
  "creationTag": {
    "versionNumber": 0,
    "lastModifiedBy": {
      "login": "patrick.masi-phelps@dataiku.com"
    },
    "lastModifiedOn": 1694477395294,
    "extendedProperties": {}
  },
  "tags": [],
  "customFields": {},
  "checklists": {
    "checklists": []
  }
}